libsens/__init__.py
libsens/constant.py
libsens/function.py
libsens/analyze/__init__.py
libsens/feed/__init__.py
libsens/feed/camera.py
libsens/feed/file.py
libsens/feed/parameter.py
libsens/feed/speaker.py
libsens/feed/audio/__init__.py
libsens/feed/audio/function.py
libsens/feed/audio/parameter.py
libsens/feed/audio/prompt.py
libsens/feed/core/__init__.py
libsens/feed/core/rwlock.py
libsens/feed/core/struct.py
libsens/feed/mock/__init__.py
libsens/feed/video/__init__.py
libsens/feed/video/function.py
libsens/feed/video/parameter.py
libsens/feed/video/prompt.py
libsens/ingest/__init__.py
serve/__init__.py
libsens-0.0.0.dist-info/LICENSE
libsens-0.0.0.dist-info/METADATA
libsens-0.0.0.dist-info/WHEEL
libsens-0.0.0.dist-info/top_level.txt
libsens-0.0.0.dist-info/RECORD
